pyUltroid/__init__.py
pyUltroid/__main__.py
pyUltroid/configs.py
pyUltroid/exceptions.py
pyUltroid/loader.py
pyUltroid/version.py
pyUltroid/_misc/__init__.py
pyUltroid/_misc/_assistant.py
pyUltroid/_misc/_decorators.py
pyUltroid/_misc/_supporter.py
pyUltroid/_misc/_wrappers.py
pyUltroid/dB/__init__.py
pyUltroid/dB/_core.py
pyUltroid/dB/afk_db.py
pyUltroid/dB/antiflood_db.py
pyUltroid/dB/asst_fns.py
pyUltroid/dB/asstcmd_db.py
pyUltroid/dB/autoban_db.py
pyUltroid/dB/blacklist_chat_db.py
pyUltroid/dB/blacklist_db.py
pyUltroid/dB/botchat_db.py
pyUltroid/dB/broadcast_db.py
pyUltroid/dB/ch_db.py
pyUltroid/dB/dnd_db.py
pyUltroid/dB/echo_db.py
pyUltroid/dB/filestore_db.py
pyUltroid/dB/filter_db.py
pyUltroid/dB/forcesub_db.py
pyUltroid/dB/gban_mute_db.py
pyUltroid/dB/gcast_blacklist_db.py
pyUltroid/dB/greetings_db.py
pyUltroid/dB/logusers_db.py
pyUltroid/dB/mute_db.py
pyUltroid/dB/night_db.py
pyUltroid/dB/notes_db.py
pyUltroid/dB/nsfw_db.py
pyUltroid/dB/pmpermit_db.py
pyUltroid/dB/snips_db.py
pyUltroid/dB/vc_sudos.py
pyUltroid/dB/warn_db.py
pyUltroid/functions/FastTelethon.py
pyUltroid/functions/__init__.py
pyUltroid/functions/admins.py
pyUltroid/functions/executor.py
pyUltroid/functions/gDrive.py
pyUltroid/functions/google_image.py
pyUltroid/functions/helper.py
pyUltroid/functions/info.py
pyUltroid/functions/misc.py
pyUltroid/functions/tools.py
pyUltroid/functions/ytdl.py
pyUltroid/startup/BaseClient.py
pyUltroid/startup/__init__.py
pyUltroid/startup/_database.py
pyUltroid/startup/_extra.py
pyUltroid/startup/connections.py
pyUltroid/startup/funcs.py
pyUltroid/startup/loader.py
pyUltroid/startup/utils.py
py_Ultroid-2022.6.6.dist-info/LICENSE
py_Ultroid-2022.6.6.dist-info/METADATA
py_Ultroid-2022.6.6.dist-info/WHEEL
py_Ultroid-2022.6.6.dist-info/top_level.txt
py_Ultroid-2022.6.6.dist-info/RECORD
