Metadata-Version: 2.1
Name: py-Ultroid
Version: 2022.6.6
Summary: A Secure and Powerful Python-Telethon Based Library For Ultroid Userbot.
Home-page: https://github.com/TeamUltroid/pyUltroid
Author: TeamUltroid
Author-email: teamultroid@protonmail.ch
License: GNU AFFERO GENERAL PUBLIC LICENSE (v3)
Project-URL: Bug Tracker, https://github.com/TeamUltroid/pyUltroid/issues
Project-URL: Documentation, https://ultroid.tech
Project-URL: Source Code, https://github.com/TeamUltroid/pyUltroid
Classifier: Programming Language :: Python :: 3
Classifier: Programming Language :: Python :: 3.8
Classifier: Programming Language :: Python :: 3.9
Classifier: Programming Language :: Python :: 3.10
Classifier: License :: OSI Approved :: GNU General Public License v3 (GPLv3)
Classifier: Operating System :: OS Independent
Requires-Python: >3.7, <3.11
License-File: LICENSE
Requires-Dist: redis
Requires-Dist: hiredis
Requires-Dist: python-decouple
Requires-Dist: python-dotenv
